pyintuition/__init__.py
pyintuition/client.py
pyintuition-0.0.5.dist-info/DESCRIPTION.rst
pyintuition-0.0.5.dist-info/METADATA
pyintuition-0.0.5.dist-info/RECORD
pyintuition-0.0.5.dist-info/WHEEL
pyintuition-0.0.5.dist-info/metadata.json
pyintuition-0.0.5.dist-info/top_level.txt
