Metadata-Version: 2.0
Name: pyintuition
Version: 0.0.5
Summary: A library for the Intuit QuickBase API.
Home-page: https://github.com/trobertsca/pyintuition
Author: Timothy Roberts
Author-email: timothy@trobertsca.com
License: UNKNOWN
Keywords: quickbase api
Platform: UNKNOWN
Classifier: Development Status :: 2 - Pre-Alpha
Classifier: Intended Audience :: Developers
Classifier: Topic :: Software Development :: Libraries
Classifier: Topic :: Software Development :: Libraries :: Python Modules
Classifier: License :: OSI Approved :: MIT License
Classifier: Programming Language :: Python :: 3.6
Requires-Dist: requests
Requires-Dist: xmltodict
Provides-Extra: test
Requires-Dist: pytest; extra == 'test'
